{
	"type": "FeatureCollection",
	"features": [
		{
			"type": "Feature",
			"geometry": {
				"type": "MultiPolygon",
				"coordinates": [
					[
						[
							[
								-75.35,
								45.18
							],
							[
								-75.43,
								45.31
							],
							[
								-75.25,
								45.36
							],
							[
								-75.34,
								45.54
							],
							[
								-75.35,
								45.54
							],
							[
								-75.45,
								45.52
							],
							[
								-75.58,
								45.47
							],
							[
								-75.68,
								45.46
							],
							[
								-75.7,
								45.43
							],
							[
								-75.8,
								45.38
							],
							[
								-75.9,
								45.4
							],
							[
								-75.99,
								45.48
							],
							[
								-76.09,
								45.51
							],
							[
								-76.2,
								45.52
							],
							[
								-76.25,
								45.47
							],
							[
								-76.3,
								45.46
							],
							[
								-76.35,
								45.41
							],
							[
								-76.21,
								45.3
							],
							[
								-75.94,
								45.08
							],
							[
								-75.82,
								44.96
							],
							[
								-75.81,
								44.98
							],
							[
								-75.59,
								45.08
							],
							[
								-75.35,
								45.18
							]
						]
					],
					[
						[
							[
								-75.35,
								45.54
							],
							[
								-75.36,
								45.6
							],
							[
								-75.45,
								45.59
							],
							[
								-75.44,
								45.55
							],
							[
								-75.54,
								45.56
							],
							[
								-75.72,
								45.55
							],
							[
								-75.8,
								45.47
							],
							[
								-75.91,
								45.48
							],
							[
								-75.9,
								45.4
							],
							[
								-75.8,
								45.38
							],
							[
								-75.7,
								45.43
							],
							[
								-75.68,
								45.46
							],
							[
								-75.58,
								45.47
							],
							[
								-75.45,
								45.52
							],
							[
								-75.35,
								45.54
							]
						]
					]
				]
			},
			"properties": {
				"PRUID": "NCR",
				"PRENAME": "National Capital Region"
			}
		}
	]
}